{
  "name": "mobile",
  "domain": "engineering",
  "resources": {
    "_context": [],
    "_experience": [],
    "_formats": [],
    "_playbooks": [],
    "_tools": []
  },
  "skills": {
    "android-clean-architecture": [
      "SKILL.md"
    ],
    "compose-multiplatform-patterns": [
      "SKILL.md"
    ],
    "dart-flutter-patterns": [
      "SKILL.md"
    ],
    "swift-actor-persistence": [
      "SKILL.md"
    ],
    "swift-concurrency-6-2": [
      "SKILL.md"
    ],
    "swift-protocol-di-testing": [
      "SKILL.md"
    ],
    "swiftui-patterns": [
      "SKILL.md"
    ]
  }
}
